plexosdb/__init__.py
plexosdb/__main__.py
plexosdb/checks.py
plexosdb/db.py
plexosdb/db_manager.py
plexosdb/enums.py
plexosdb/exceptions.py
plexosdb/py.typed
plexosdb/queries/object_properties.sql
plexosdb/queries/object_query.sql
plexosdb/queries/property.sql
plexosdb/queries/property_query.sql
plexosdb/queries/simple_object_query.sql
plexosdb/schema.sql
plexosdb/utils.py
plexosdb/xml_handler.py
plexosdb-1.3.0.dist-info/WHEEL
plexosdb-1.3.0.dist-info/METADATA
plexosdb-1.3.0.dist-info/RECORD
