Metadata-Version: 2.3
Name: plexosdb
Version: 1.3.0
Summary: SQLite API for plexos XMLs
Keywords: PLEXOS,Database,SQLite
Author: Pedro Andres Sanchez Perez, Kodi Obika, mcllerena
Author-email: Pedro Andres Sanchez Perez <psanchez@nrel.gov>, Kodi Obika <kodi.obika@nrel.gov>, mcllerena <mcllerena@users.noreply.github.com>
License: BSD 3-Clause License
Classifier: Development Status :: 5 - Production/Stable
Classifier: Intended Audience :: Developers
Classifier: License :: OSI Approved :: BSD License
Classifier: Topic :: Software Development :: Build Tools
Classifier: Programming Language :: Python :: 3.11
Classifier: Programming Language :: Python :: 3.12
Classifier: Programming Language :: Python :: 3.13
Classifier: Programming Language :: Python :: 3.14
Classifier: Topic :: Scientific/Engineering
Classifier: Topic :: Scientific/Engineering :: Information Analysis
Classifier: Topic :: Scientific/Engineering :: Interface Engine/Protocol Translator
Classifier: Topic :: Software Development :: Build Tools
Classifier: Topic :: Database
Classifier: Typing :: Typed
Requires-Dist: loguru
Maintainer: Pedro Andres Sanchez Perez, Kodi Obika, mcllerena
Maintainer-email: Pedro Andres Sanchez Perez <psanchez@nrel.gov>, Kodi Obika <kodi.obika@nrel.gov>, mcllerena <mcllerena@users.noreply.github.com>
Requires-Python: >=3.11, <3.15
Project-URL: Changelog, https://github.com/NREL/plexosdb/blob/master/CHANGELOG.md
Project-URL: Documentation, https://github.com/NREL/plexosdb#readme
Project-URL: Issues, https://github.com/NREL/plexosdb/issues
Project-URL: Source, https://github.com/NREL/plexosdb
